colada/__init__.py
colada-0.0.1.dist-info/DESCRIPTION.rst
colada-0.0.1.dist-info/METADATA
colada-0.0.1.dist-info/RECORD
colada-0.0.1.dist-info/WHEEL
colada-0.0.1.dist-info/metadata.json
colada-0.0.1.dist-info/top_level.txt
