Metadata-Version: 2.0
Name: colada
Version: 0.0.1
Summary: Colada Python SDK
Home-page: UNKNOWN
Author: UNKNOWN
Author-email: UNKNOWN
License: UNKNOWN
Platform: UNKNOWN
